{
	"Card": "HTR-1-006",
	"Effects": [{
		"Type": "Action",
		"Conditions": [
			{
			"Trigger": {
				"Name": "_t_when_played",
				"Scope": "self"
			},
			"Parameters":
				[]
			}
			],
		"Actions": [
			{
            "Method": "e_look_top_and_move",
            "Arguments": {
                "Scope": "my_board",
                "Destination": "my_deck",
                "Choose": "No",
                "Order": [0],
                "Value": 7,
                "Draw": {
                    "Value": 1,
                    "Tags": ["Specified Slot"]
                }
                }
			}
			]
	},{}
	]
}
